discrete_fourier/__init__.py
discrete_fourier/df_common_functions.py
discrete_fourier/discrete_fourier.py
discrete_fourier-0.3.2.dist-info/METADATA
discrete_fourier-0.3.2.dist-info/WHEEL
discrete_fourier-0.3.2.dist-info/licenses/LICENSE
discrete_fourier-0.3.2.dist-info/RECORD
