Metadata-Version: 2.4
Name: discrete-fourier
Version: 0.3.2
Summary: Calculate discrete Fourier coefficients, detect periods, and validate periodic patterns
License: MIT
License-File: LICENSE
Author: Ricardo Marcelo Alvarez
Author-email: rmalvarezkai@gmail.com
Requires-Python: >=3.13,<4.0
Classifier: License :: OSI Approved :: MIT License
Classifier: Programming Language :: Python :: 3
Classifier: Programming Language :: Python :: 3.13
Classifier: Programming Language :: Python :: 3.14
Requires-Dist: numpy (>=1.20.0)
